[
  {
    "trend_arrow": "45_UP", 
    "display_time": "2016-11-26T04:21:41-08:00", 
    "noise": 1, 
    "system_time": "2016-11-26T12:21:12-08:00", 
    "direction": "FortyFiveUp", 
    "sgv": 187, 
    "dateString": "2016-11-26T04:21:41-08:00", 
    "date": 1480162901000, 
    "unfiltered": 183584, 
    "filtered": 179104, 
    "device": "openaps://indy-e3/cgm", 
    "rssi": 186, 
    "type": "sgv", 
    "glucose": 187
  }, 
  {
    "trend_arrow": "45_UP", 
    "display_time": "2016-11-26T04:16:41-08:00", 
    "noise": 1, 
    "system_time": "2016-11-26T12:16:12-08:00", 
    "direction": "FortyFiveUp", 
    "sgv": 185, 
    "dateString": "2016-11-26T04:16:41-08:00", 
    "date": 1480162601000, 
    "unfiltered": 181504, 
    "filtered": 172960, 
    "device": "openaps://indy-e3/cgm", 
    "rssi": 186, 
    "type": "sgv", 
    "glucose": 185
  }
]