[
  {
    "trend_arrow": "FLAT", 
    "display_time": "2017-07-03T04:36:37-07:00", 
    "noise": 1, 
    "system_time": "2017-07-03T10:24:23-07:00", 
    "direction": "Flat", 
    "sgv": 101, 
    "dateString": "2017-07-03T04:36:37-07:00", 
    "date": 1499081797000, 
    "unfiltered": 124896, 
    "filtered": 122032, 
    "device": "openaps://indy-e3/cgm", 
    "rssi": 432, 
    "type": "sgv", 
    "glucose": 101
  }, 
  {
    "trend_arrow": "FLAT", 
    "display_time": "2017-07-03T04:31:37-07:00", 
    "noise": 1, 
    "system_time": "2017-07-03T10:19:22-07:00", 
    "direction": "Flat", 
    "sgv": 99, 
    "dateString": "2017-07-03T04:31:37-07:00", 
    "date": 1499081497000, 
    "unfiltered": 122928, 
    "filtered": 118656, 
    "device": "openaps://indy-e3/cgm", 
    "rssi": 184, 
    "type": "sgv", 
    "glucose": 99
  }
]