[
  {
    "trend_arrow": "FLAT", 
    "display_time": "2016-12-09T02:04:51-08:00", 
    "noise": 1, 
    "system_time": "2016-12-09T10:04:17-08:00", 
    "direction": "Flat", 
    "sgv": 75, 
    "dateString": "2016-12-09T02:04:51-08:00", 
    "date": 1481277891000, 
    "unfiltered": 100736, 
    "filtered": 104912, 
    "device": "openaps://indy-e3/cgm", 
    "rssi": 183, 
    "type": "sgv", 
    "glucose": 75
  }, 
  {
    "trend_arrow": "FLAT", 
    "display_time": "2016-12-09T01:59:51-08:00", 
    "noise": 1, 
    "system_time": "2016-12-09T09:59:17-08:00", 
    "direction": "Flat", 
    "sgv": 78, 
    "dateString": "2016-12-09T01:59:51-08:00", 
    "date": 1481277591000, 
    "unfiltered": 103472, 
    "filtered": 108528, 
    "device": "openaps://indy-e3/cgm", 
    "rssi": 443, 
    "type": "sgv", 
    "glucose": 78
  }
]