[
  {
    "trend_arrow": "FLAT", 
    "display_time": "2016-12-01T01:10:11-08:00", 
    "noise": 1, 
    "system_time": "2016-12-01T09:09:39-08:00", 
    "direction": "Flat", 
    "sgv": 149, 
    "dateString": "2016-12-01T01:10:11-08:00", 
    "date": 1480583411000, 
    "unfiltered": 164416, 
    "filtered": 167200, 
    "device": "openaps://indy-e3/cgm", 
    "rssi": 194, 
    "type": "sgv", 
    "glucose": 149
  }, 
  {
    "trend_arrow": "45_DOWN", 
    "display_time": "2016-12-01T01:05:11-08:00", 
    "noise": 1, 
    "system_time": "2016-12-01T09:04:39-08:00", 
    "direction": "FortyFiveDown", 
    "sgv": 150, 
    "dateString": "2016-12-01T01:05:11-08:00", 
    "date": 1480583111000, 
    "unfiltered": 165952, 
    "filtered": 171328, 
    "device": "openaps://indy-e3/cgm", 
    "rssi": 194, 
    "type": "sgv", 
    "glucose": 150
  }
]