[
  {
    "trend_arrow": "FLAT", 
    "display_time": "2016-11-26T10:51:41-08:00", 
    "noise": 1, 
    "system_time": "2016-11-26T18:51:11-08:00", 
    "direction": "Flat", 
    "sgv": 144, 
    "dateString": "2016-11-26T10:51:41-08:00", 
    "date": 1480186301000, 
    "unfiltered": 149472, 
    "filtered": 148800, 
    "device": "openaps://indy-e3/cgm", 
    "rssi": 419, 
    "type": "sgv", 
    "glucose": 144
  }, 
  {
    "trend_arrow": "FLAT", 
    "display_time": "2016-11-26T10:46:40-08:00", 
    "noise": 1, 
    "system_time": "2016-11-26T18:46:11-08:00", 
    "direction": "Flat", 
    "sgv": 145, 
    "dateString": "2016-11-26T10:46:40-08:00", 
    "date": 1480186000000, 
    "unfiltered": 150432, 
    "filtered": 146080, 
    "device": "openaps://indy-e3/cgm", 
    "rssi": 163, 
    "type": "sgv", 
    "glucose": 145
  }
]