[
  {
    "display_time": "2016-12-10T13:05:50-08:00", 
    "system_time": "2016-12-10T21:05:15-08:00", 
    "dateString": "2016-12-10T13:05:50-08:00", 
    "date": 1481403950000, 
    "unfiltered": 4294967295, 
    "filtered": 4294967295, 
    "device": "openaps://indy-e3/cgm", 
    "rssi": 16572, 
    "sgv": -1, 
    "type": "sgv"
  }, 
  {
    "display_time": "2016-12-10T13:00:50-08:00", 
    "system_time": "2016-12-10T21:00:15-08:00", 
    "dateString": "2016-12-10T13:00:50-08:00", 
    "date": 1481403650000, 
    "unfiltered": 4294967295, 
    "filtered": 4294967295, 
    "device": "openaps://indy-e3/cgm", 
    "rssi": 16563, 
    "sgv": -1, 
    "type": "sgv"
  }
]