[
  {
    "trend_arrow": "FLAT", 
    "display_time": "2016-11-29T19:15:14-08:00", 
    "noise": 1, 
    "system_time": "2016-11-30T03:14:43-08:00", 
    "direction": "Flat", 
    "sgv": 113, 
    "dateString": "2016-11-29T19:15:14-08:00", 
    "date": 1480475714000, 
    "unfiltered": 132320, 
    "filtered": 134528, 
    "device": "openaps://indy-e3/cgm", 
    "rssi": 195, 
    "type": "sgv", 
    "glucose": 113
  }, 
  {
    "trend_arrow": "FLAT", 
    "display_time": "2016-11-29T19:10:14-08:00", 
    "noise": 1, 
    "system_time": "2016-11-30T03:09:43-08:00", 
    "direction": "Flat", 
    "sgv": 114, 
    "dateString": "2016-11-29T19:10:14-08:00", 
    "date": 1480475414000, 
    "unfiltered": 132992, 
    "filtered": 135776, 
    "device": "openaps://indy-e3/cgm", 
    "rssi": 169, 
    "type": "sgv", 
    "glucose": 114
  }
]