[
  {
    "trend_arrow": "NOT_COMPUTABLE", 
    "display_time": "2016-11-27T21:05:19-08:00", 
    "noise": 4, 
    "system_time": "2016-11-28T05:04:48-08:00", 
    "direction": "NOT COMPUTABLE", 
    "sgv": 10, 
    "dateString": "2016-11-27T21:05:19-08:00", 
    "date": 1480309519000, 
    "unfiltered": 250624, 
    "filtered": 289344, 
    "device": "openaps://indy-e3/cgm", 
    "rssi": 187, 
    "type": "sgv", 
    "glucose": 10
  }, 
  {
    "trend_arrow": "NOT_COMPUTABLE", 
    "display_time": "2016-11-27T21:00:20-08:00", 
    "noise": 4, 
    "system_time": "2016-11-28T04:59:48-08:00", 
    "direction": "NOT COMPUTABLE", 
    "sgv": 10, 
    "dateString": "2016-11-27T21:00:20-08:00", 
    "date": 1480309220000, 
    "unfiltered": 246528, 
    "filtered": 294016, 
    "device": "openaps://indy-e3/cgm", 
    "rssi": 447, 
    "type": "sgv", 
    "glucose": 10
  }
]