[
  {
    "trend_arrow": "DOUBLE_UP", 
    "display_time": "2016-11-29T21:45:14-08:00", 
    "noise": 1, 
    "system_time": "2016-11-30T05:44:42-08:00", 
    "direction": "DoubleUp", 
    "sgv": 220, 
    "dateString": "2016-11-29T21:45:14-08:00", 
    "date": 1480484714000, 
    "unfiltered": 241952, 
    "filtered": 212992, 
    "device": "openaps://indy-e3/cgm", 
    "rssi": 187, 
    "type": "sgv", 
    "glucose": 220
  }, 
  {
    "trend_arrow": "DOUBLE_UP", 
    "display_time": "2016-11-29T21:40:14-08:00", 
    "noise": 1, 
    "system_time": "2016-11-30T05:39:42-08:00", 
    "direction": "DoubleUp", 
    "sgv": 204, 
    "dateString": "2016-11-29T21:40:14-08:00", 
    "date": 1480484414000, 
    "unfiltered": 225536, 
    "filtered": 192768, 
    "device": "openaps://indy-e3/cgm", 
    "rssi": 185, 
    "type": "sgv", 
    "glucose": 204
  }
]