[
  {
    "trend_arrow": "FLAT", 
    "display_time": "2016-12-08T22:09:51-08:00", 
    "noise": 1, 
    "system_time": "2016-12-09T06:09:18-08:00", 
    "direction": "Flat", 
    "sgv": 101, 
    "dateString": "2016-12-08T22:09:51-08:00", 
    "device": "openaps://indy-e3/cgm", 
    "unfiltered": 126192, 
    "rssi": 177, 
    "date": 1481263791000, 
    "filtered": 129712, 
    "type": "sgv", 
    "glucose": 101
  }, 
  {
    "trend_arrow": "FLAT", 
    "display_time": "2016-12-08T22:04:51-08:00", 
    "noise": 1, 
    "system_time": "2016-12-09T06:04:18-08:00", 
    "direction": "Flat", 
    "sgv": 102, 
    "dateString": "2016-12-08T22:04:51-08:00", 
    "device": "openaps://indy-e3/cgm", 
    "unfiltered": 126784, 
    "rssi": 441, 
    "date": 1481263491000, 
    "filtered": 131392, 
    "type": "sgv", 
    "glucose": 102
  }
]