[
  {
    "trend_arrow": "FLAT", 
    "system_time": "2016-12-05T13:09:28", 
    "noise": 1, 
    "direction": "Flat", 
    "sgv": 86, 
    "display_time": "2016-12-05T05:10:01", 
    "date": 1480943401000.0, 
    "dateString": "2016-12-05T05:10:01", 
    "unfiltered": 117584, 
    "filtered": 124512, 
    "device": "openaps://indy-e3/cgm", 
    "rssi": 172, 
    "type": "sgv", 
    "glucose": 86
  }, 
  {
    "trend_arrow": "FLAT", 
    "system_time": "2016-12-05T13:04:28", 
    "noise": 1, 
    "direction": "Flat", 
    "sgv": 90, 
    "display_time": "2016-12-05T05:05:01", 
    "date": 1480943101000.0, 
    "dateString": "2016-12-05T05:05:01", 
    "unfiltered": 121840, 
    "filtered": 128048, 
    "device": "openaps://indy-e3/cgm", 
    "rssi": 196, 
    "type": "sgv", 
    "glucose": 90
  }, 
  {
    "trend_arrow": "FLAT", 
    "system_time": "2016-12-05T12:59:28", 
    "noise": 1, 
    "direction": "Flat", 
    "sgv": 94, 
    "display_time": "2016-12-05T05:00:01", 
    "date": 1480942801000.0, 
    "dateString": "2016-12-05T05:00:01", 
    "unfiltered": 126384, 
    "filtered": 131328, 
    "device": "openaps://indy-e3/cgm", 
    "rssi": 193, 
    "type": "sgv", 
    "glucose": 94
  }, 
  {
    "trend_arrow": "FLAT", 
    "system_time": "2016-12-05T12:54:28", 
    "noise": 1, 
    "direction": "Flat", 
    "sgv": 98, 
    "display_time": "2016-12-05T04:55:01", 
    "date": 1480942501000.0, 
    "dateString": "2016-12-05T04:55:01", 
    "unfiltered": 130944, 
    "filtered": 135008, 
    "device": "openaps://indy-e3/cgm", 
    "rssi": 197, 
    "type": "sgv", 
    "glucose": 98
  }, 
  {
    "trend_arrow": "FLAT", 
    "system_time": "2016-12-05T12:49:28", 
    "noise": 1, 
    "direction": "Flat", 
    "sgv": 100, 
    "display_time": "2016-12-05T04:50:01", 
    "date": 1480942201000.0, 
    "dateString": "2016-12-05T04:50:01", 
    "unfiltered": 132864, 
    "filtered": 139328, 
    "device": "openaps://indy-e3/cgm", 
    "rssi": 188, 
    "type": "sgv", 
    "glucose": 100
  }, 
  {
    "trend_arrow": "FLAT", 
    "system_time": "2016-12-05T12:44:28", 
    "noise": 1, 
    "direction": "Flat", 
    "sgv": 103, 
    "display_time": "2016-12-05T04:45:01", 
    "date": 1480941901000.0, 
    "dateString": "2016-12-05T04:45:01", 
    "unfiltered": 136128, 
    "filtered": 143456, 
    "device": "openaps://indy-e3/cgm", 
    "rssi": 185, 
    "type": "sgv", 
    "glucose": 103
  }
]