[
  {
    "trend_arrow": "NOT_COMPUTABLE", 
    "system_time": "2016-11-28T00:09:48", 
    "noise": 1, 
    "direction": "NOT COMPUTABLE", 
    "sgv": 211, 
    "display_time": "2016-11-27T16:10:20", 
    "date": 1480291820000.0, 
    "dateString": "2016-11-27T16:10:20", 
    "unfiltered": 204256, 
    "filtered": 207872, 
    "device": "openaps://indy-e3/cgm", 
    "rssi": 187, 
    "type": "sgv", 
    "glucose": 211
  }, 
  {
    "trend_arrow": "45_DOWN", 
    "system_time": "2016-11-27T23:54:49", 
    "noise": 1, 
    "direction": "FortyFiveDown", 
    "sgv": 220, 
    "display_time": "2016-11-27T15:55:20", 
    "date": 1480290920000.0, 
    "dateString": "2016-11-27T15:55:20", 
    "unfiltered": 211776, 
    "filtered": 207488, 
    "device": "openaps://indy-e3/cgm", 
    "rssi": 424, 
    "type": "sgv", 
    "glucose": 220
  }
]