[
  {
    "trend_arrow": "FLAT", 
    "display_time": "2017-07-04T11:41:32-07:00", 
    "noise": 1, 
    "system_time": "2017-07-04T17:29:17-07:00", 
    "direction": "Flat", 
    "sgv": 65, 
    "dateString": "2017-07-04T11:41:32-07:00", 
    "device": "openaps://indy-e3/cgm", 
    "unfiltered": 92960, 
    "rssi": 180, 
    "date": 1499193692000, 
    "filtered": 94848, 
    "type": "sgv", 
    "glucose": 65
  }, 
  {
    "trend_arrow": "FLAT", 
    "display_time": "2017-07-04T11:36:32-07:00", 
    "noise": 1, 
    "system_time": "2017-07-04T17:24:17-07:00", 
    "direction": "Flat", 
    "sgv": 66, 
    "dateString": "2017-07-04T11:36:32-07:00", 
    "device": "openaps://indy-e3/cgm", 
    "unfiltered": 94128, 
    "rssi": 179, 
    "date": 1499193392000, 
    "filtered": 95904, 
    "type": "sgv", 
    "glucose": 66
  }
]