[
  {
    "trend_arrow": "FLAT", 
    "display_time": "2017-07-08T02:01:02-07:00", 
    "noise": 1, 
    "direction": "Flat", 
    "system_time": "2017-07-08T10:00:55-07:00", 
    "sgv": 136, 
    "dateString": "2017-07-08T02:01:02-07:00", 
    "device": "openaps://indy-e3/cgm", 
    "unfiltered": 144672, 
    "rssi": 187, 
    "date": 1499504462000.0, 
    "filtered": 141504, 
    "type": "sgv", 
    "glucose": 136
  }, 
  {
    "trend_arrow": "FLAT", 
    "display_time": "2017-07-08T01:56:02-07:00", 
    "noise": 1, 
    "direction": "Flat", 
    "system_time": "2017-07-08T09:55:55-07:00", 
    "sgv": 132, 
    "dateString": "2017-07-08T01:56:02-07:00", 
    "device": "openaps://indy-e3/cgm", 
    "unfiltered": 141344, 
    "rssi": 193, 
    "date": 1499504162000.0, 
    "filtered": 141472, 
    "type": "sgv", 
    "glucose": 132
  }, 
  {
    "trend_arrow": "FLAT", 
    "display_time": "2017-07-08T01:51:02-07:00", 
    "noise": 1, 
    "direction": "Flat", 
    "system_time": "2017-07-08T09:50:55-07:00", 
    "sgv": 132, 
    "dateString": "2017-07-08T01:51:02-07:00", 
    "device": "openaps://indy-e3/cgm", 
    "unfiltered": 141120, 
    "rssi": 189, 
    "date": 1499503862000.0, 
    "filtered": 141312, 
    "type": "sgv", 
    "glucose": 132
  }, 
  {
    "trend_arrow": "FLAT", 
    "display_time": "2017-07-08T01:46:03-07:00", 
    "noise": 1, 
    "direction": "Flat", 
    "system_time": "2017-07-08T09:45:55-07:00", 
    "sgv": 130, 
    "dateString": "2017-07-08T01:46:03-07:00", 
    "device": "openaps://indy-e3/cgm", 
    "unfiltered": 139712, 
    "rssi": 430, 
    "date": 1499503563000.0, 
    "filtered": 139968, 
    "type": "sgv", 
    "glucose": 130
  }, 
  {
    "trend_arrow": "FLAT", 
    "display_time": "2017-07-08T01:41:02-07:00", 
    "noise": 1, 
    "direction": "Flat", 
    "system_time": "2017-07-08T09:40:55-07:00", 
    "sgv": 133, 
    "dateString": "2017-07-08T01:41:02-07:00", 
    "device": "openaps://indy-e3/cgm", 
    "unfiltered": 142048, 
    "rssi": 188, 
    "date": 1499503262000.0, 
    "filtered": 137504, 
    "type": "sgv", 
    "glucose": 133
  }, 
  {
    "trend_arrow": "FLAT", 
    "display_time": "2017-07-08T01:36:02-07:00", 
    "noise": 1, 
    "direction": "Flat", 
    "system_time": "2017-07-08T09:35:55-07:00", 
    "sgv": 131, 
    "dateString": "2017-07-08T01:36:02-07:00", 
    "device": "openaps://indy-e3/cgm", 
    "unfiltered": 139744, 
    "rssi": 193, 
    "date": 1499502962000.0, 
    "filtered": 134464, 
    "type": "sgv", 
    "glucose": 131
  }
]