[
  {
    "trend_arrow": "45_DOWN", 
    "display_time": "2016-11-25T12:26:44-08:00", 
    "noise": 1, 
    "direction": "FortyFiveDown", 
    "system_time": "2016-11-25T20:26:14-08:00", 
    "sgv": 84, 
    "dateString": "2016-11-25T12:26:44-08:00", 
    "device": "openaps://indy-e3/cgm", 
    "unfiltered": 101776, 
    "rssi": 191, 
    "date": 1480105604000.0, 
    "filtered": 115104, 
    "type": "sgv", 
    "glucose": 84
  }, 
  {
    "trend_arrow": "45_DOWN", 
    "display_time": "2016-11-25T12:21:44-08:00", 
    "noise": 1, 
    "direction": "FortyFiveDown", 
    "system_time": "2016-11-25T20:21:14-08:00", 
    "sgv": 102, 
    "dateString": "2016-11-25T12:21:44-08:00", 
    "device": "openaps://indy-e3/cgm", 
    "unfiltered": 117056, 
    "rssi": 187, 
    "date": 1480105304000.0, 
    "filtered": 119856, 
    "type": "sgv", 
    "glucose": 102
  }, 
  {
    "trend_arrow": "45_DOWN", 
    "display_time": "2016-11-25T12:16:44-08:00", 
    "noise": 1, 
    "direction": "FortyFiveDown", 
    "system_time": "2016-11-25T20:16:14-08:00", 
    "sgv": 105, 
    "dateString": "2016-11-25T12:16:44-08:00", 
    "device": "openaps://indy-e3/cgm", 
    "unfiltered": 120080, 
    "rssi": 196, 
    "date": 1480105004000.0, 
    "filtered": 125664, 
    "type": "sgv", 
    "glucose": 105
  }, 
  {
    "trend_arrow": "SINGLE_DOWN", 
    "display_time": "2016-11-25T12:11:44-08:00", 
    "noise": 1, 
    "direction": "SingleDown", 
    "system_time": "2016-11-25T20:11:14-08:00", 
    "sgv": 103, 
    "dateString": "2016-11-25T12:11:44-08:00", 
    "device": "openaps://indy-e3/cgm", 
    "unfiltered": 118208, 
    "rssi": 190, 
    "date": 1480104704000.0, 
    "filtered": 133696, 
    "type": "sgv", 
    "glucose": 103
  }, 
  {
    "trend_arrow": "45_DOWN", 
    "display_time": "2016-11-25T12:06:44-08:00", 
    "noise": 1, 
    "direction": "FortyFiveDown", 
    "system_time": "2016-11-25T20:06:14-08:00", 
    "sgv": 119, 
    "dateString": "2016-11-25T12:06:44-08:00", 
    "device": "openaps://indy-e3/cgm", 
    "unfiltered": 131264, 
    "rssi": 182, 
    "date": 1480104404000.0, 
    "filtered": 142880, 
    "type": "sgv", 
    "glucose": 119
  }, 
  {
    "trend_arrow": "45_DOWN", 
    "display_time": "2016-11-25T12:01:44-08:00", 
    "noise": 1, 
    "direction": "FortyFiveDown", 
    "system_time": "2016-11-25T20:01:14-08:00", 
    "sgv": 126, 
    "dateString": "2016-11-25T12:01:44-08:00", 
    "device": "openaps://indy-e3/cgm", 
    "unfiltered": 137472, 
    "rssi": 173, 
    "date": 1480104104000.0, 
    "filtered": 151616, 
    "type": "sgv", 
    "glucose": 126
  }
]