[
  {
    "trend_arrow": "FLAT", 
    "display_time": "2016-12-10T07:20:52-08:00", 
    "noise": 1, 
    "system_time": "2016-12-10T15:20:16-08:00", 
    "direction": "Flat", 
    "sgv": 111, 
    "dateString": "2016-12-10T07:20:52-08:00", 
    "device": "openaps://indy-e3/cgm", 
    "unfiltered": 114432, 
    "rssi": 16562, 
    "date": 1481383252000, 
    "filtered": 117808, 
    "type": "sgv", 
    "glucose": 111
  }, 
  {
    "trend_arrow": "FLAT", 
    "display_time": "2016-12-10T07:15:52-08:00", 
    "noise": 1, 
    "system_time": "2016-12-10T15:15:16-08:00", 
    "direction": "Flat", 
    "sgv": 112, 
    "dateString": "2016-12-10T07:15:52-08:00", 
    "device": "openaps://indy-e3/cgm", 
    "unfiltered": 116192, 
    "rssi": 16563, 
    "date": 1481382952000, 
    "filtered": 119712, 
    "type": "sgv", 
    "glucose": 112
  }
]