[
  {
    "trend_arrow": "FLAT", 
    "display_time": "2016-12-11T18:04:45-08:00", 
    "noise": 1, 
    "system_time": "2016-12-12T02:04:10-08:00", 
    "direction": "Flat", 
    "sgv": 107, 
    "dateString": "2016-12-11T18:04:45-08:00", 
    "device": "openaps://indy-e3/cgm", 
    "unfiltered": 137248, 
    "rssi": 168, 
    "date": 1481508285000, 
    "filtered": 144672, 
    "type": "sgv", 
    "glucose": 107
  }, 
  {
    "trend_arrow": "FLAT", 
    "display_time": "2016-12-11T17:59:45-08:00", 
    "noise": 1, 
    "system_time": "2016-12-12T01:59:10-08:00", 
    "direction": "Flat", 
    "sgv": 113, 
    "dateString": "2016-12-11T17:59:45-08:00", 
    "device": "openaps://indy-e3/cgm", 
    "unfiltered": 143904, 
    "rssi": 165, 
    "date": 1481507985000, 
    "filtered": 148192, 
    "type": "sgv", 
    "glucose": 113
  }
]