[
  {
    "trend_arrow": "SINGLE_DOWN", 
    "display_time": "2016-12-11T16:39:45-08:00", 
    "noise": 1, 
    "direction": "SingleDown", 
    "system_time": "2016-12-12T00:39:10-08:00", 
    "sgv": 241, 
    "dateString": "2016-12-11T16:39:45-08:00", 
    "device": "openaps://indy-e3/cgm", 
    "unfiltered": 284096, 
    "rssi": 176, 
    "date": 1481503185000.0, 
    "filtered": 308928, 
    "type": "sgv", 
    "glucose": 241
  }, 
  {
    "trend_arrow": "FLAT", 
    "display_time": "2016-12-11T16:34:45-08:00", 
    "noise": 1, 
    "direction": "Flat", 
    "system_time": "2016-12-12T00:34:10-08:00", 
    "sgv": 257, 
    "dateString": "2016-12-11T16:34:45-08:00", 
    "device": "openaps://indy-e3/cgm", 
    "unfiltered": 301568, 
    "rssi": 179, 
    "date": 1481502885000.0, 
    "filtered": 318464, 
    "type": "sgv", 
    "glucose": 257
  }, 
  {
    "trend_arrow": "FLAT", 
    "display_time": "2016-12-11T16:29:46-08:00", 
    "noise": 1, 
    "direction": "Flat", 
    "system_time": "2016-12-12T00:29:10-08:00", 
    "sgv": 270, 
    "dateString": "2016-12-11T16:29:46-08:00", 
    "device": "openaps://indy-e3/cgm", 
    "unfiltered": 316480, 
    "rssi": 449, 
    "date": 1481502586000.0, 
    "filtered": 323648, 
    "type": "sgv", 
    "glucose": 270
  }
]