[
  {
    "trend_arrow": "FLAT", 
    "display_time": "2016-12-12T05:54:44-08:00", 
    "noise": 1, 
    "direction": "Flat", 
    "system_time": "2016-12-12T13:54:08-08:00", 
    "sgv": 116, 
    "dateString": "2016-12-12T05:54:44-08:00", 
    "device": "openaps://indy-e3/cgm", 
    "unfiltered": 147584, 
    "rssi": 188, 
    "date": 1481550884000.0, 
    "filtered": 144608, 
    "type": "sgv", 
    "glucose": 116
  }, 
  {
    "trend_arrow": "FLAT", 
    "display_time": "2016-12-12T05:49:44-08:00", 
    "noise": 1, 
    "direction": "Flat", 
    "system_time": "2016-12-12T13:49:08-08:00", 
    "sgv": 114, 
    "dateString": "2016-12-12T05:49:44-08:00", 
    "device": "openaps://indy-e3/cgm", 
    "unfiltered": 145408, 
    "rssi": 187, 
    "date": 1481550584000.0, 
    "filtered": 142496, 
    "type": "sgv", 
    "glucose": 114
  }, 
  {
    "trend_arrow": "FLAT", 
    "display_time": "2016-12-12T05:44:44-08:00", 
    "noise": 1, 
    "direction": "Flat", 
    "system_time": "2016-12-12T13:44:08-08:00", 
    "sgv": 112, 
    "dateString": "2016-12-12T05:44:44-08:00", 
    "device": "openaps://indy-e3/cgm", 
    "unfiltered": 143232, 
    "rssi": 187, 
    "date": 1481550284000.0, 
    "filtered": 139488, 
    "type": "sgv", 
    "glucose": 112
  }, 
  {
    "trend_arrow": "FLAT", 
    "display_time": "2016-12-12T05:39:44-08:00", 
    "noise": 1, 
    "direction": "Flat", 
    "system_time": "2016-12-12T13:39:09-08:00", 
    "sgv": 110, 
    "dateString": "2016-12-12T05:39:44-08:00", 
    "device": "openaps://indy-e3/cgm", 
    "unfiltered": 140992, 
    "rssi": 187, 
    "date": 1481549984000.0, 
    "filtered": 135392, 
    "type": "sgv", 
    "glucose": 110
  }, 
  {
    "trend_arrow": "FLAT", 
    "display_time": "2016-12-12T05:34:44-08:00", 
    "noise": 1, 
    "direction": "Flat", 
    "system_time": "2016-12-12T13:34:08-08:00", 
    "sgv": 108, 
    "dateString": "2016-12-12T05:34:44-08:00", 
    "device": "openaps://indy-e3/cgm", 
    "unfiltered": 138080, 
    "rssi": 186, 
    "date": 1481549684000.0, 
    "filtered": 130592, 
    "type": "sgv", 
    "glucose": 108
  }, 
  {
    "trend_arrow": "FLAT", 
    "display_time": "2016-12-12T05:29:44-08:00", 
    "noise": 1, 
    "direction": "Flat", 
    "system_time": "2016-12-12T13:29:08-08:00", 
    "sgv": 104, 
    "dateString": "2016-12-12T05:29:44-08:00", 
    "device": "openaps://indy-e3/cgm", 
    "unfiltered": 133792, 
    "rssi": 187, 
    "date": 1481549384000.0, 
    "filtered": 125792, 
    "type": "sgv", 
    "glucose": 104
  }
]