[
  {
    "trend_arrow": "FLAT", 
    "display_time": "2016-11-28T05:20:18-08:00", 
    "noise": 1, 
    "system_time": "2016-11-28T13:19:47-08:00", 
    "direction": "Flat", 
    "sgv": 106, 
    "dateString": "2016-11-28T05:20:18-08:00", 
    "device": "openaps://indy-e3/cgm", 
    "unfiltered": 120528, 
    "rssi": 190, 
    "date": 1480339218000, 
    "filtered": 121568, 
    "type": "sgv", 
    "glucose": 106
  }, 
  {
    "trend_arrow": "FLAT", 
    "display_time": "2016-11-28T05:15:19-08:00", 
    "noise": 1, 
    "system_time": "2016-11-28T13:14:47-08:00", 
    "direction": "Flat", 
    "sgv": 106, 
    "dateString": "2016-11-28T05:15:19-08:00", 
    "device": "openaps://indy-e3/cgm", 
    "unfiltered": 120960, 
    "rssi": 444, 
    "date": 1480338919000, 
    "filtered": 120784, 
    "type": "sgv", 
    "glucose": 106
  }
]