[
  {
    "trend_arrow": "FLAT", 
    "display_time": "2016-12-01T05:00:10-08:00", 
    "noise": 1, 
    "system_time": "2016-12-01T12:59:39-08:00", 
    "direction": "Flat", 
    "sgv": 112, 
    "dateString": "2016-12-01T05:00:10-08:00", 
    "device": "openaps://indy-e3/cgm", 
    "unfiltered": 131136, 
    "rssi": 192, 
    "date": 1480597210000, 
    "filtered": 133120, 
    "type": "sgv", 
    "glucose": 112
  }, 
  {
    "trend_arrow": "FLAT", 
    "display_time": "2016-12-01T04:55:11-08:00", 
    "noise": 1, 
    "system_time": "2016-12-01T12:54:39-08:00", 
    "direction": "Flat", 
    "sgv": 113, 
    "dateString": "2016-12-01T04:55:11-08:00", 
    "device": "openaps://indy-e3/cgm", 
    "unfiltered": 132576, 
    "rssi": 441, 
    "date": 1480596911000, 
    "filtered": 133760, 
    "type": "sgv", 
    "glucose": 113
  }
]