[
  {
    "trend_arrow": "FLAT", 
    "display_time": "2016-12-06T04:24:59-08:00", 
    "noise": 1, 
    "system_time": "2016-12-06T12:24:25-08:00", 
    "direction": "Flat", 
    "sgv": 126, 
    "dateString": "2016-12-06T04:24:59-08:00", 
    "device": "openaps://indy-e3/cgm", 
    "unfiltered": 157920, 
    "rssi": 196, 
    "date": 1481027099000, 
    "filtered": 152384, 
    "type": "sgv", 
    "glucose": 126
  }, 
  {
    "trend_arrow": "FLAT", 
    "display_time": "2016-12-06T04:19:59-08:00", 
    "noise": 1, 
    "system_time": "2016-12-06T12:19:25-08:00", 
    "direction": "Flat", 
    "sgv": 122, 
    "dateString": "2016-12-06T04:19:59-08:00", 
    "device": "openaps://indy-e3/cgm", 
    "unfiltered": 154336, 
    "rssi": 196, 
    "date": 1481026799000, 
    "filtered": 149120, 
    "type": "sgv", 
    "glucose": 122
  }
]