[
  {
    "trend_arrow": "FLAT", 
    "display_time": "2016-12-01T20:45:08-08:00", 
    "noise": 1, 
    "direction": "Flat", 
    "system_time": "2016-12-02T04:44:37-08:00", 
    "sgv": 109, 
    "dateString": "2016-12-01T20:45:08-08:00", 
    "device": "openaps://indy-e3/cgm", 
    "unfiltered": 132160, 
    "rssi": 184, 
    "date": 1480653908000.0, 
    "filtered": 139264, 
    "type": "sgv", 
    "glucose": 109
  }, 
  {
    "trend_arrow": "FLAT", 
    "display_time": "2016-12-01T20:40:08-08:00", 
    "noise": 1, 
    "direction": "Flat", 
    "system_time": "2016-12-02T04:39:37-08:00", 
    "sgv": 114, 
    "dateString": "2016-12-01T20:40:08-08:00", 
    "device": "openaps://indy-e3/cgm", 
    "unfiltered": 136928, 
    "rssi": 180, 
    "date": 1480653608000.0, 
    "filtered": 140992, 
    "type": "sgv", 
    "glucose": 114
  }, 
  {
    "trend_arrow": "FLAT", 
    "display_time": "2016-12-01T20:35:09-08:00", 
    "noise": 1, 
    "direction": "Flat", 
    "system_time": "2016-12-02T04:34:37-08:00", 
    "sgv": 119, 
    "dateString": "2016-12-01T20:35:09-08:00", 
    "device": "openaps://indy-e3/cgm", 
    "unfiltered": 140800, 
    "rssi": 192, 
    "date": 1480653309000.0, 
    "filtered": 140960, 
    "type": "sgv", 
    "glucose": 119
  }, 
  {
    "trend_arrow": "FLAT", 
    "display_time": "2016-12-01T20:30:09-08:00", 
    "noise": 1, 
    "direction": "Flat", 
    "system_time": "2016-12-02T04:29:37-08:00", 
    "sgv": 120, 
    "dateString": "2016-12-01T20:30:09-08:00", 
    "device": "openaps://indy-e3/cgm", 
    "unfiltered": 142112, 
    "rssi": 184, 
    "date": 1480653009000.0, 
    "filtered": 140032, 
    "type": "sgv", 
    "glucose": 120
  }, 
  {
    "trend_arrow": "FLAT", 
    "display_time": "2016-12-01T20:25:09-08:00", 
    "noise": 1, 
    "direction": "Flat", 
    "system_time": "2016-12-02T04:24:37-08:00", 
    "sgv": 118, 
    "dateString": "2016-12-01T20:25:09-08:00", 
    "device": "openaps://indy-e3/cgm", 
    "unfiltered": 140544, 
    "rssi": 180, 
    "date": 1480652709000.0, 
    "filtered": 139072, 
    "type": "sgv", 
    "glucose": 118
  }, 
  {
    "trend_arrow": "FLAT", 
    "display_time": "2016-12-01T20:20:09-08:00", 
    "noise": 1, 
    "direction": "Flat", 
    "system_time": "2016-12-02T04:19:37-08:00", 
    "sgv": 118, 
    "dateString": "2016-12-01T20:20:09-08:00", 
    "device": "openaps://indy-e3/cgm", 
    "unfiltered": 140032, 
    "rssi": 180, 
    "date": 1480652409000.0, 
    "filtered": 138176, 
    "type": "sgv", 
    "glucose": 118
  }
]