[
  {
    "trend_arrow": "45_DOWN", 
    "display_time": "2016-12-17T21:29:30-08:00", 
    "noise": 1, 
    "system_time": "2016-12-18T05:28:54-08:00", 
    "direction": "FortyFiveDown", 
    "sgv": 92, 
    "dateString": "2016-12-17T21:29:30-08:00", 
    "device": "openaps://indy-e3/cgm", 
    "unfiltered": 118704, 
    "rssi": 428, 
    "date": 1482038970000, 
    "filtered": 126048, 
    "type": "sgv", 
    "glucose": 92
  }, 
  {
    "trend_arrow": "45_DOWN", 
    "display_time": "2016-12-17T21:24:30-08:00", 
    "noise": 1, 
    "system_time": "2016-12-18T05:23:53-08:00", 
    "direction": "FortyFiveDown", 
    "sgv": 97, 
    "dateString": "2016-12-17T21:24:30-08:00", 
    "device": "openaps://indy-e3/cgm", 
    "unfiltered": 123040, 
    "rssi": 177, 
    "date": 1482038670000, 
    "filtered": 134016, 
    "type": "sgv", 
    "glucose": 97
  }
]