[
  {
    "trend_arrow": "FLAT", 
    "display_time": "2016-11-26T11:31:40-08:00", 
    "noise": 1, 
    "direction": "Flat", 
    "system_time": "2016-11-26T19:31:11-08:00", 
    "sgv": 122, 
    "dateString": "2016-11-26T11:31:40-08:00", 
    "device": "openaps://indy-e3/cgm", 
    "unfiltered": 131744, 
    "rssi": 161, 
    "date": 1480188700000.0, 
    "filtered": 135904, 
    "type": "sgv", 
    "glucose": 122
  }, 
  {
    "trend_arrow": "FLAT", 
    "display_time": "2016-11-26T11:26:41-08:00", 
    "noise": 1, 
    "direction": "Flat", 
    "system_time": "2016-11-26T19:26:11-08:00", 
    "sgv": 128, 
    "dateString": "2016-11-26T11:26:41-08:00", 
    "device": "openaps://indy-e3/cgm", 
    "unfiltered": 136320, 
    "rssi": 421, 
    "date": 1480188401000.0, 
    "filtered": 137472, 
    "type": "sgv", 
    "glucose": 128
  }, 
  {
    "trend_arrow": "FLAT", 
    "display_time": "2016-11-26T11:21:41-08:00", 
    "noise": 1, 
    "direction": "Flat", 
    "system_time": "2016-11-26T19:21:12-08:00", 
    "sgv": 129, 
    "dateString": "2016-11-26T11:21:41-08:00", 
    "device": "openaps://indy-e3/cgm", 
    "unfiltered": 137344, 
    "rssi": 681, 
    "date": 1480188101000.0, 
    "filtered": 138944, 
    "type": "sgv", 
    "glucose": 129
  }, 
  {
    "trend_arrow": "FLAT", 
    "display_time": "2016-11-26T11:16:41-08:00", 
    "noise": 1, 
    "direction": "Flat", 
    "system_time": "2016-11-26T19:16:12-08:00", 
    "sgv": 127, 
    "dateString": "2016-11-26T11:16:41-08:00", 
    "device": "openaps://indy-e3/cgm", 
    "unfiltered": 136064, 
    "rssi": 681, 
    "date": 1480187801000.0, 
    "filtered": 140928, 
    "type": "sgv", 
    "glucose": 127
  }, 
  {
    "trend_arrow": "FLAT", 
    "display_time": "2016-11-26T11:11:41-08:00", 
    "noise": 1, 
    "direction": "Flat", 
    "system_time": "2016-11-26T19:11:12-08:00", 
    "sgv": 135, 
    "dateString": "2016-11-26T11:11:41-08:00", 
    "device": "openaps://indy-e3/cgm", 
    "unfiltered": 142528, 
    "rssi": 679, 
    "date": 1480187501000.0, 
    "filtered": 143520, 
    "type": "sgv", 
    "glucose": 135
  }, 
  {
    "trend_arrow": "FLAT", 
    "display_time": "2016-11-26T11:06:41-08:00", 
    "noise": 1, 
    "direction": "Flat", 
    "system_time": "2016-11-26T19:06:11-08:00", 
    "sgv": 133, 
    "dateString": "2016-11-26T11:06:41-08:00", 
    "device": "openaps://indy-e3/cgm", 
    "unfiltered": 140928, 
    "rssi": 420, 
    "date": 1480187201000.0, 
    "filtered": 146464, 
    "type": "sgv", 
    "glucose": 133
  }
]