[
  {
    "trend_arrow": "45_UP", 
    "display_time": "2017-07-04T12:16:32-07:00", 
    "noise": 1, 
    "system_time": "2017-07-04T18:04:17-07:00", 
    "direction": "FortyFiveUp", 
    "sgv": 90, 
    "dateString": "2017-07-04T12:16:32-07:00", 
    "device": "openaps://indy-e3/cgm", 
    "unfiltered": 114736, 
    "rssi": 175, 
    "date": 1499195792000, 
    "filtered": 98304, 
    "type": "sgv", 
    "glucose": 90
  }, 
  {
    "trend_arrow": "45_UP", 
    "display_time": "2017-07-04T12:11:32-07:00", 
    "noise": 1, 
    "system_time": "2017-07-04T17:59:17-07:00", 
    "direction": "FortyFiveUp", 
    "sgv": 77, 
    "dateString": "2017-07-04T12:11:32-07:00", 
    "device": "openaps://indy-e3/cgm", 
    "unfiltered": 103744, 
    "rssi": 175, 
    "date": 1499195492000, 
    "filtered": 92448, 
    "type": "sgv", 
    "glucose": 77
  }
]