[
  {
    "trend_arrow": "FLAT", 
    "display_time": "2017-07-08T09:26:02-07:00", 
    "noise": 1, 
    "system_time": "2017-07-08T17:25:55-07:00", 
    "direction": "Flat", 
    "sgv": 105, 
    "dateString": "2017-07-08T09:26:02-07:00", 
    "device": "openaps://indy-e3/cgm", 
    "unfiltered": 124464, 
    "rssi": 442, 
    "date": 1499531162000, 
    "filtered": 126368, 
    "type": "sgv", 
    "glucose": 105
  }, 
  {
    "trend_arrow": "FLAT", 
    "display_time": "2017-07-08T09:21:01-07:00", 
    "noise": 1, 
    "system_time": "2017-07-08T17:20:54-07:00", 
    "direction": "Flat", 
    "sgv": 107, 
    "dateString": "2017-07-08T09:21:01-07:00", 
    "device": "openaps://indy-e3/cgm", 
    "unfiltered": 125872, 
    "rssi": 189, 
    "date": 1499530861000, 
    "filtered": 127248, 
    "type": "sgv", 
    "glucose": 107
  }
]