[
  {
    "trend_arrow": "FLAT", 
    "display_time": "2016-11-25T10:26:44-08:00", 
    "noise": 1, 
    "direction": "Flat", 
    "system_time": "2016-11-25T18:26:14-08:00", 
    "sgv": 81, 
    "dateString": "2016-11-25T10:26:44-08:00", 
    "device": "openaps://indy-e3/cgm", 
    "unfiltered": 100000, 
    "rssi": 198, 
    "date": 1480098404000.0, 
    "filtered": 98272, 
    "type": "sgv", 
    "glucose": 81
  }, 
  {
    "trend_arrow": "FLAT", 
    "display_time": "2016-11-25T10:21:44-08:00", 
    "noise": 1, 
    "direction": "Flat", 
    "system_time": "2016-11-25T18:21:14-08:00", 
    "sgv": 82, 
    "dateString": "2016-11-25T10:21:44-08:00", 
    "device": "openaps://indy-e3/cgm", 
    "unfiltered": 100848, 
    "rssi": 180, 
    "date": 1480098104000.0, 
    "filtered": 96512, 
    "type": "sgv", 
    "glucose": 82
  }, 
  {
    "trend_arrow": "FLAT", 
    "display_time": "2016-11-25T10:16:44-08:00", 
    "noise": 1, 
    "direction": "Flat", 
    "system_time": "2016-11-25T18:16:14-08:00", 
    "sgv": 81, 
    "dateString": "2016-11-25T10:16:44-08:00", 
    "device": "openaps://indy-e3/cgm", 
    "unfiltered": 99360, 
    "rssi": 165, 
    "date": 1480097804000.0, 
    "filtered": 95856, 
    "type": "sgv", 
    "glucose": 81
  }, 
  {
    "trend_arrow": "FLAT", 
    "display_time": "2016-11-25T10:11:44-08:00", 
    "noise": 1, 
    "direction": "Flat", 
    "system_time": "2016-11-25T18:11:15-08:00", 
    "sgv": 74, 
    "dateString": "2016-11-25T10:11:44-08:00", 
    "device": "openaps://indy-e3/cgm", 
    "unfiltered": 93680, 
    "rssi": 449, 
    "date": 1480097504000.0, 
    "filtered": 96592, 
    "type": "sgv", 
    "glucose": 74
  }, 
  {
    "trend_arrow": "FLAT", 
    "display_time": "2016-11-25T10:06:44-08:00", 
    "noise": 1, 
    "direction": "Flat", 
    "system_time": "2016-11-25T18:06:14-08:00", 
    "sgv": 77, 
    "dateString": "2016-11-25T10:06:44-08:00", 
    "device": "openaps://indy-e3/cgm", 
    "unfiltered": 96064, 
    "rssi": 185, 
    "date": 1480097204000.0, 
    "filtered": 98864, 
    "type": "sgv", 
    "glucose": 77
  }, 
  {
    "trend_arrow": "FLAT", 
    "display_time": "2016-11-25T10:01:44-08:00", 
    "noise": 1, 
    "direction": "Flat", 
    "system_time": "2016-11-25T18:01:15-08:00", 
    "sgv": 82, 
    "dateString": "2016-11-25T10:01:44-08:00", 
    "device": "openaps://indy-e3/cgm", 
    "unfiltered": 100160, 
    "rssi": 178, 
    "date": 1480096904000.0, 
    "filtered": 102272, 
    "type": "sgv", 
    "glucose": 82
  }
]