[
  {
    "trend_arrow": "FLAT", 
    "display_time": "2017-07-08T03:11:02-07:00", 
    "noise": 1, 
    "system_time": "2017-07-08T11:10:54-07:00", 
    "direction": "Flat", 
    "sgv": 155, 
    "dateString": "2017-07-08T03:11:02-07:00", 
    "device": "openaps://indy-e3/cgm", 
    "unfiltered": 163872, 
    "rssi": 190, 
    "date": 1499508662000, 
    "filtered": 164864, 
    "type": "sgv", 
    "glucose": 155
  }, 
  {
    "trend_arrow": "FLAT", 
    "display_time": "2017-07-08T03:06:02-07:00", 
    "noise": 1, 
    "system_time": "2017-07-08T11:05:54-07:00", 
    "direction": "Flat", 
    "sgv": 158, 
    "dateString": "2017-07-08T03:06:02-07:00", 
    "device": "openaps://indy-e3/cgm", 
    "unfiltered": 166080, 
    "rssi": 189, 
    "date": 1499508362000, 
    "filtered": 164384, 
    "type": "sgv", 
    "glucose": 158
  }
]