[
  {
    "trend_arrow": "FLAT", 
    "display_time": "2016-12-08T00:04:54-08:00", 
    "noise": 1, 
    "direction": "Flat", 
    "system_time": "2016-12-08T08:04:20-08:00", 
    "sgv": 243, 
    "dateString": "2016-12-08T00:04:54-08:00", 
    "device": "openaps://indy-e3/cgm", 
    "unfiltered": 264704, 
    "rssi": 173, 
    "date": 1481184294000.0, 
    "filtered": 265600, 
    "type": "sgv", 
    "glucose": 243
  }, 
  {
    "trend_arrow": "FLAT", 
    "display_time": "2016-12-07T23:59:53-08:00", 
    "noise": 1, 
    "direction": "Flat", 
    "system_time": "2016-12-08T07:59:20-08:00", 
    "sgv": 245, 
    "dateString": "2016-12-07T23:59:53-08:00", 
    "device": "openaps://indy-e3/cgm", 
    "unfiltered": 266432, 
    "rssi": 185, 
    "date": 1481183993000.0, 
    "filtered": 269824, 
    "type": "sgv", 
    "glucose": 245
  }, 
  {
    "trend_arrow": "FLAT", 
    "display_time": "2016-12-07T23:54:53-08:00", 
    "noise": 1, 
    "direction": "Flat", 
    "system_time": "2016-12-08T07:54:20-08:00", 
    "sgv": 244, 
    "dateString": "2016-12-07T23:54:53-08:00", 
    "device": "openaps://indy-e3/cgm", 
    "unfiltered": 265856, 
    "rssi": 170, 
    "date": 1481183693000.0, 
    "filtered": 275008, 
    "type": "sgv", 
    "glucose": 244
  }, 
  {
    "trend_arrow": "FLAT", 
    "display_time": "2016-12-07T23:49:53-08:00", 
    "noise": 1, 
    "direction": "Flat", 
    "system_time": "2016-12-08T07:49:20-08:00", 
    "sgv": 248, 
    "dateString": "2016-12-07T23:49:53-08:00", 
    "device": "openaps://indy-e3/cgm", 
    "unfiltered": 268928, 
    "rssi": 177, 
    "date": 1481183393000.0, 
    "filtered": 278528, 
    "type": "sgv", 
    "glucose": 248
  }, 
  {
    "trend_arrow": "FLAT", 
    "display_time": "2016-12-07T23:44:53-08:00", 
    "noise": 1, 
    "direction": "Flat", 
    "system_time": "2016-12-08T07:44:20-08:00", 
    "sgv": 257, 
    "dateString": "2016-12-07T23:44:53-08:00", 
    "device": "openaps://indy-e3/cgm", 
    "unfiltered": 277312, 
    "rssi": 185, 
    "date": 1481183093000.0, 
    "filtered": 278720, 
    "type": "sgv", 
    "glucose": 257
  }, 
  {
    "trend_arrow": "FLAT", 
    "display_time": "2016-12-07T23:39:54-08:00", 
    "noise": 1, 
    "direction": "Flat", 
    "system_time": "2016-12-08T07:39:21-08:00", 
    "sgv": 260, 
    "dateString": "2016-12-07T23:39:54-08:00", 
    "device": "openaps://indy-e3/cgm", 
    "unfiltered": 280448, 
    "rssi": 441, 
    "date": 1481182794000.0, 
    "filtered": 276224, 
    "type": "sgv", 
    "glucose": 260
  }
]